[
  {
    "file": "quikdown.d.ts",
    "size": 3007,
    "type": "types"
  },
  {
    "file": "quikdown.esm.js",
    "size": 27195,
    "format": "ESM",
    "minified": false
  },
  {
    "file": "quikdown.esm.min.js",
    "size": 9251,
    "format": "ESM",
    "minified": true,
    "sri": "sha384-C8L7rQkpEoW+mnmpm7V6WIXLDec4UBmxb1saSmUGwpZWX1H1ueBzE4kPVmZVugqG",
    "gzFile": "quikdown.esm.min.js.gz",
    "gzSize": 3573
  },
  {
    "file": "quikdown.umd.js",
    "size": 30131,
    "format": "UMD",
    "minified": false
  },
  {
    "file": "quikdown.umd.min.js",
    "size": 9473,
    "format": "UMD",
    "minified": true,
    "sri": "sha384-aEHOJPrgUZ93nhCcWrQQHUSvEy18MITE2DEbt3mB1ZSZpxRGJcNw9OCye9pwrFPO",
    "gzFile": "quikdown.umd.min.js.gz",
    "gzSize": 3649
  },
  {
    "file": "quikdown_ast.d.ts",
    "size": 3756,
    "type": "types"
  },
  {
    "file": "quikdown_ast.esm.js",
    "size": 15944,
    "format": "ESM",
    "minified": false
  },
  {
    "file": "quikdown_ast.esm.min.js",
    "size": 5047,
    "format": "ESM",
    "minified": true,
    "sri": "sha384-WdQTnumdl0JZ/BMjlNUwRnEp72EPp+Oc1J0yR/2D94oYFJllpDhgqZq8PHSp6b3Z",
    "gzFile": "quikdown_ast.esm.min.js.gz",
    "gzSize": 1911
  },
  {
    "file": "quikdown_ast.umd.js",
    "size": 18036,
    "format": "UMD",
    "minified": false
  },
  {
    "file": "quikdown_ast.umd.min.js",
    "size": 5273,
    "format": "UMD",
    "minified": true,
    "sri": "sha384-dT1JbOQI1p7XqK1io5ETcQ+Lw0NVUEsd8TlX1ASrk3I8GvSsjV/drPry33UK5fNa",
    "gzFile": "quikdown_ast.umd.min.js.gz",
    "gzSize": 1989
  },
  {
    "file": "quikdown_ast_html.d.ts",
    "size": 1778,
    "type": "types"
  },
  {
    "file": "quikdown_ast_html.esm.js",
    "size": 33121,
    "format": "ESM",
    "minified": false
  },
  {
    "file": "quikdown_ast_html.esm.min.js",
    "size": 11710,
    "format": "ESM",
    "minified": true,
    "sri": "sha384-YuEDoVOaOD2IVxoD87UzSprqml2zjAjKfPjoDD+hje3+ZU00gFivtOJld8LyZiTm",
    "gzFile": "quikdown_ast_html.esm.min.js.gz",
    "gzSize": 4115
  },
  {
    "file": "quikdown_ast_html.umd.js",
    "size": 37034,
    "format": "UMD",
    "minified": false
  },
  {
    "file": "quikdown_ast_html.umd.min.js",
    "size": 11941,
    "format": "UMD",
    "minified": true,
    "sri": "sha384-m1gN2Mi96riRGTvjcvF5QHcQVaEKL7XGbllZFz3OMYHvXWy1pXbxyDSrhumxabu5",
    "gzFile": "quikdown_ast_html.umd.min.js.gz",
    "gzSize": 4191
  },
  {
    "file": "quikdown_bd.d.ts",
    "size": 3485,
    "type": "types"
  },
  {
    "file": "quikdown_bd.esm.js",
    "size": 44514,
    "format": "ESM",
    "minified": false
  },
  {
    "file": "quikdown_bd.esm.min.js",
    "size": 14198,
    "format": "ESM",
    "minified": true,
    "sri": "sha384-7viXQRVJSF1/GFqZHg9li4CrMVG7UMdp2bV5xBd8oLQbBjqRR7HBlJaEUqrH65X+",
    "gzFile": "quikdown_bd.esm.min.js.gz",
    "gzSize": 5078
  },
  {
    "file": "quikdown_bd.umd.js",
    "size": 49057,
    "format": "UMD",
    "minified": false
  },
  {
    "file": "quikdown_bd.umd.min.js",
    "size": 14423,
    "format": "UMD",
    "minified": true,
    "sri": "sha384-XsFK1DsqBYsJDVGgLvWXu322imjR+FeL0klG7vfqGRkCRab9Z8BASbAULvDNklJK",
    "gzFile": "quikdown_bd.umd.min.js.gz",
    "gzSize": 5156
  },
  {
    "file": "quikdown_edit.d.ts",
    "size": 6517,
    "type": "types"
  },
  {
    "file": "quikdown_edit.esm.js",
    "size": 205780,
    "format": "ESM",
    "minified": false
  },
  {
    "file": "quikdown_edit.esm.min.js",
    "size": 82313,
    "format": "ESM",
    "minified": true,
    "sri": "sha384-In9GLyRaOS2gl76eM9B5VliayFG5tGknNUmDLy/eh65cz64KF/8BqTlPlx7YNu0r",
    "gzFile": "quikdown_edit.esm.min.js.gz",
    "gzSize": 21308
  },
  {
    "file": "quikdown_edit.umd.js",
    "size": 223762,
    "format": "UMD",
    "minified": false
  },
  {
    "file": "quikdown_edit.umd.min.js",
    "size": 82556,
    "format": "UMD",
    "minified": true,
    "sri": "sha384-XDOe7uNAdj24C7XWjNWWnurTCWEQTk8+PcZMg/cIZRx/A6l7m8/W+sNa+RS2/GS3",
    "gzFile": "quikdown_edit.umd.min.js.gz",
    "gzSize": 21401
  },
  {
    "file": "quikdown_json.d.ts",
    "size": 1204,
    "type": "types"
  },
  {
    "file": "quikdown_json.esm.js",
    "size": 17191,
    "format": "ESM",
    "minified": false
  },
  {
    "file": "quikdown_json.esm.min.js",
    "size": 5291,
    "format": "ESM",
    "minified": true,
    "sri": "sha384-xRFl6cQ3kxxUTzLaOtuaeEzoWz4LerVtEFkPjMlFS3dqU/fk6XgbzmVppaEC/bIZ",
    "gzFile": "quikdown_json.esm.min.js.gz",
    "gzSize": 1980
  },
  {
    "file": "quikdown_json.umd.js",
    "size": 19424,
    "format": "UMD",
    "minified": false
  },
  {
    "file": "quikdown_json.umd.min.js",
    "size": 5518,
    "format": "UMD",
    "minified": true,
    "sri": "sha384-sYyfWDYCMIIHMysAw/SyQwRHnoowrD97mTyn8o/oa5lw2/Ej+Ms3SLQ+Fv4zDJNK",
    "gzFile": "quikdown_json.umd.min.js.gz",
    "gzSize": 2059
  },
  {
    "file": "quikdown_yaml.d.ts",
    "size": 1362,
    "type": "types"
  },
  {
    "file": "quikdown_yaml.esm.js",
    "size": 21580,
    "format": "ESM",
    "minified": false
  },
  {
    "file": "quikdown_yaml.esm.min.js",
    "size": 6810,
    "format": "ESM",
    "minified": true,
    "sri": "sha384-69K2dcju+DMmL+9YfEUbykjS8H5mcNb+bsh5Ww9MIFWcSsqKXpzZJJBGu4GnaWjO",
    "gzFile": "quikdown_yaml.esm.min.js.gz",
    "gzSize": 2405
  },
  {
    "file": "quikdown_yaml.umd.js",
    "size": 24365,
    "format": "UMD",
    "minified": false
  },
  {
    "file": "quikdown_yaml.umd.min.js",
    "size": 7037,
    "format": "UMD",
    "minified": true,
    "sri": "sha384-7+mke/hS2xCQxkjBv3enAYPklPcjPPEnOMVec55f7kjbh+KObXyxs13zJkBTCuSY",
    "gzFile": "quikdown_yaml.umd.min.js.gz",
    "gzSize": 2482
  }
]
